pycoupler/__init__.py
pycoupler/_version.py
pycoupler/config.py
pycoupler/coupler.py
pycoupler/data.py
pycoupler/release.py
pycoupler/run.py
pycoupler/utils.py
pycoupler-1.6.2.dist-info/METADATA
pycoupler-1.6.2.dist-info/WHEEL
pycoupler-1.6.2.dist-info/licenses/LICENSE.md
pycoupler-1.6.2.dist-info/RECORD
