Metadata-Version: 2.4
Name: pycoupler
Version: 1.6.2
Summary: dynamic model coupling of LPJmL
Project-URL: Homepage, https://github.com/PIK-LPJmL/pycoupler
Project-URL: Issues, https://github.com/PIK-LPJmL/pycoupler/issues
Project-URL: Documentation, https://github.com/PIK-LPJmL/pycoupler/wiki
Project-URL: Repository, https://github.com/PIK-LPJmL/pycoupler
Author-email: Jannes Breier <jannes.breier@pik-potsdam.de>
License: ### GNU AFFERO GENERAL PUBLIC LICENSE
License-File: LICENSE.md
Keywords: ABM,DGVM,LPJmL,copan:CORE,model coupling
Classifier: Development Status :: 4 - Beta
Classifier: Intended Audience :: Developers
Classifier: Intended Audience :: Science/Research
Classifier: Operating System :: OS Independent
Classifier: Programming Language :: Python
Classifier: Programming Language :: Python :: 3.9
Classifier: Programming Language :: Python :: 3.10
Classifier: Programming Language :: Python :: 3.11
Classifier: Programming Language :: Python :: 3.12
Classifier: Topic :: Scientific/Engineering
Classifier: Topic :: Software Development :: Libraries
Requires-Python: >=3.9
Requires-Dist: fuzzywuzzy>=0.18.0
Requires-Dist: levenshtein>=0.12.2
Requires-Dist: netcdf4>=1.5.8
Requires-Dist: numpy>=1.20.3
Requires-Dist: ruamel-yaml>=0.17.16
Requires-Dist: scipy>=1.7.1
Requires-Dist: xarray>=0.21.1
Provides-Extra: dev
Requires-Dist: black; extra == 'dev'
Requires-Dist: flake8; extra == 'dev'
Requires-Dist: pytest; extra == 'dev'
Requires-Dist: pytest-cov; extra == 'dev'
Requires-Dist: pytest-subprocess; extra == 'dev'
Requires-Dist: sphinx; extra == 'dev'
